README.md
setup.py
bloxroute_pyelliptic.egg-info/PKG-INFO
bloxroute_pyelliptic.egg-info/SOURCES.txt
bloxroute_pyelliptic.egg-info/dependency_links.txt
bloxroute_pyelliptic.egg-info/top_level.txt
pyelliptic/__init__.py
pyelliptic/arithmetic.py
pyelliptic/cipher.py
pyelliptic/ecc.py
pyelliptic/hash.py
pyelliptic/openssl.py